mdc/__init__.py
mdc/context.py
mdc/decorators.py
mdc-1.2.0.dist-info/LICENSE.txt
mdc-1.2.0.dist-info/METADATA
mdc-1.2.0.dist-info/WHEEL
mdc-1.2.0.dist-info/top_level.txt
mdc-1.2.0.dist-info/RECORD
