Metadata-Version: 2.1
Name: mdc
Version: 1.2.0
Summary: Mapped Diagnostic Context (MDC) library for python
Home-page: https://github.com/afriemann/mdc
Author: Aljosha Friemann
Author-email: a.friemann@automate.wtf
License: UNKNOWN
Keywords: logging,mdc,context
Platform: UNKNOWN
Classifier: Topic :: System :: Logging
Classifier: Programming Language :: Python :: 2
Classifier: Programming Language :: Python :: 3
Requires-Dist: future
Requires-Dist: python-json-logger
